README.md
setup.py
bintray/__init__.py
bintray/bintray.py
bintray/logger.py
bintray/requester.py
bintray/requirements.txt
bintray/requirements_test.txt
bintray/utils.py
bintray_python.egg-info/PKG-INFO
bintray_python.egg-info/SOURCES.txt
bintray_python.egg-info/dependency_links.txt
bintray_python.egg-info/requires.txt
bintray_python.egg-info/top_level.txt