Metadata-Version: 2.1
Name: bintray-python
Version: 0.7.0
Summary: Python Wrapper for Bintray API
Home-page: https://github.com/uilianries/bintray-python
Author: Uilian Ries
Author-email: uilianries@gmail.com
License: MIT
Keywords: jfrog,bintray,api,libraries,developer,manager,dependency,package,python,wrapper
Platform: UNKNOWN
Classifier: Development Status :: 4 - Beta
Classifier: Intended Audience :: Developers
Classifier: Topic :: Software Development :: Build Tools
Classifier: License :: OSI Approved :: MIT License
Classifier: Programming Language :: Python :: 3
Provides-Extra: test
